{
    "type": "FeatureCollection",
    "features": [
        {
            "id": "7456582d-b956-4735-8d0c-76ed018365f6",
            "type": "Feature",
            "geometry": {
              "type": "Polygon",
              "coordinates": [
                [
                  [
                    53.059941542,
                    8.833608627
                  ],
                  [
                    53.059103319,
                    8.834788799
                  ],
                  [
                    53.059632046,
                    8.837063313
                  ],
                  [
                    53.05789109,
                    8.840668201
                  ],
                  [
                    53.057710543,
                    8.838093281
                  ],
                  [
                    53.057749232,
                    8.836054802
                  ],
                  [
                    53.058368248,
                    8.834295273
                  ],
                  [
                    53.059180694,
                    8.830325603
                  ],
                  [
                    53.059941542,
                    8.833608627
                  ]
                ]
              ]
            },
            "properties": {
              "mode": "polygon",
              "name": "Heizenberg's"
            }
          },
        {
            "id": "4c824cfd-1f72-49c2-9e11-d6af4505a8a7",
            "type": "Feature",
            "geometry": {
                "type": "Polygon",
                "coordinates": [
                    [
                        [
                            53.062380877,
                            8.820193314
                        ],
                        [
                            53.062045609,
                            8.820815586
                        ],
                        [
                            53.061271903,
                            8.821287655
                        ],
                        [
                            53.0607303,
                            8.822896981
                        ],
                        [
                            53.059737344,
                            8.827746415
                        ],
                        [
                            53.061052683,
                            8.828475975
                        ],
                        [
                            53.060910835,
                            8.830042386
                        ],
                        [
                            53.061787708,
                            8.830578827
                        ],
                        [
                            53.063489823,
                            8.821630978
                        ],
                        [
                            53.062509825,
                            8.821867012
                        ],
                        [
                            53.062380877,
                            8.820193314
                        ]
                    ]
                ]
            },
            "properties": {
                "mode": "polygon",
                "name": "Bremen musicians camp"
            }
        },
        {
            "id": "0433ef66-f78f-41f8-913d-16f69bfca6db",
            "type": "Feature",
            "geometry": {
                "type": "Polygon",
                "coordinates": [
                    [
                        [
                            50.971454703,
                            10.978339535
                        ],
                        [
                            50.971427679,
                            10.978425366
                        ],
                        [
                            50.966427946,
                            10.982588155
                        ],
                        [
                            50.966157675,
                            10.984347683
                        ],
                        [
                            50.968914366,
                            10.998037678
                        ],
                        [
                            50.972778866,
                            10.994304043
                        ],
                        [
                            50.971900201,
                            10.986541118
                        ],
                        [
                            50.971454703,
                            10.978339535
                        ]
                    ]
                ]
            },
            "properties": {
                "mode": "polygon",
                "selected": true,
                "name": "Gardens or cemetry maybe"
            }
        },
        {
            "id": "a96ca8d2-e544-4458-9edd-48d44509a7b8",
            "type": "Feature",
            "geometry": {
                "type": "Polygon",
                "coordinates": [
                    [
                        [
                            50.088546761,
                            8.6791002
                        ],
                        [
                            50.088546761,
                            8.6791002
                        ],
                        [
                            50.088546761,
                            8.6791002
                        ],
                        [
                            50.093062225,
                            8.679958506
                        ],
                        [
                            50.095154613,
                            8.681331797
                        ],
                        [
                            50.096696314,
                            8.68407838
                        ],
                        [
                            50.098127849,
                            8.686824962
                        ],
                        [
                            50.099669454,
                            8.689399882
                        ],
                        [
                            50.100550348,
                            8.692489787
                        ],
                        [
                            50.100550348,
                            8.695923015
                        ],
                        [
                            50.098898658,
                            8.698154612
                        ],
                        [
                            50.09713679,
                            8.700729533
                        ],
                        [
                            50.094934367,
                            8.702102824
                        ],
                        [
                            50.09251158,
                            8.702102824
                        ],
                        [
                            50.090088673,
                            8.702102824
                        ],
                        [
                            50.087775788,
                            8.702102824
                        ],
                        [
                            50.085352641,
                            8.701759501
                        ],
                        [
                            50.083810573,
                            8.699184581
                        ],
                        [
                            50.082709068,
                            8.696094676
                        ],
                        [
                            50.081827846,
                            8.69283311
                        ],
                        [
                            50.081827846,
                            8.689228221
                        ],
                        [
                            50.081937998,
                            8.685623332
                        ],
                        [
                            50.084141018,
                            8.686996623
                        ],
                        [
                            50.086013511,
                            8.689571544
                        ],
                        [
                            50.087996066,
                            8.691116496
                        ],
                        [
                            50.088656903,
                            8.691803141
                        ],
                        [
                            50.088546761,
                            8.6791002
                        ]
                    ]
                ]
            },
            "properties": {
                "mode": "freehand",
                "selected": true,
                "name": "Frankfurt 1"
            }
        },
      {
        "type": "Feature",
        "properties": {
            "name": "mercedes1",
            "color": "green"
        },
        "geometry": {
          "coordinates": [
            [
              [
                  50.972827834411845,
                  10.968020388593118
              ],
              [
                  50.97408440426818,
                  10.971137542953386
              ],
              [
                  50.97445140654085,
                  10.970725065063903
              ],
              [
                  50.9731018510395,
                  10.967643439854498
              ],
              [
                  50.972827834411845,
                  10.968020388593118
              ]
          ]
          ],
          "type": "Polygon"
        }
      },
      {
        "type": "Feature",
        "properties": {
            "name": "mercedes2",
            "color": "blue"
        },
        "geometry": {
          "coordinates": [
            [
              [
                  50.9733232998332,
                  10.970072288649476
              ],
              [
                  50.97266093547202,
                  10.97080807026299
              ],
              [
                  50.9729663792786,
                  10.972219680914321
              ],
              [
                  50.973848379893894,
                  10.971320392275572
              ],
              [
                  50.9733232998332,
                  10.970072288649476
              ]
          ]
          ],
          "type": "Polygon"
        }
      },
      {
        "type": "Feature",
        "properties": {
            "name": "mercedes3",
            "color": "indigo"
        },
        "geometry": {
          "coordinates": [
            [
              [
                  50.97297049728169,
                  10.969470651174845
              ],
              [
                  50.97265936054694,
                  10.969790813486185
              ],
              [
                  50.97234081639877,
                  10.971936721803644
              ],
              [
                  50.97251678794342,
                  10.971907446045293
              ],
              [
                  50.97282905240701,
                  10.971089182791872
              ],
              [
                  50.9726438295248,
                  10.970585644271722
              ],
              [
                  50.97284057118674,
                  10.970117638674452
              ],
              [
                  50.97308532396454,
                  10.969741807371179
              ],
              [
                  50.97297049728169,
                  10.969470651174845
              ]
          ]
          ],
          "type": "Polygon"
        }
      }
    ]
  }
